lia/__init__.py
lia/main.py
lia/bounty/__init__.py
lia/bounty/heal.py
lia/bounty/testing.py
lia/container/__init__.py
lia/container/container.py
lia/container/lxc.py
lia/container/podman.py
lia/conversation/__init__.py
lia/conversation/ask_to_proceed.py
lia/conversation/container.py
lia/conversation/decision.py
lia/conversation/emojis.py
lia/conversation/end_message.py
lia/conversation/error.py
lia/conversation/get_input.py
lia/conversation/sphinx.py
lia/conversation/start_message.py
lia/git_operations/__init__.py
lia/git_operations/push.py
lia/git_operations/verify_branch.py
lia/simplify/__init__.py
lia/simplify/verify_package.py
lia/sphinx/__init__.py
lia/sphinx/generate_docs.py
lia/support/__init__.py
lia/support/deploy.py
lia/utils/__init__.py
lia/utils/error.py
lia/utils/helper.py
spawn_lia-0.3.2.dist-info/LICENSE.txt
spawn_lia-0.3.2.dist-info/METADATA
spawn_lia-0.3.2.dist-info/WHEEL
spawn_lia-0.3.2.dist-info/entry_points.txt
spawn_lia-0.3.2.dist-info/top_level.txt
spawn_lia-0.3.2.dist-info/RECORD
