Metadata-Version: 2.1
Name: spawn-lia
Version: 0.3.2
Summary: The most wanted support
Home-page: https://codeberg.org/cap_jmk/lia
Author: Julian M. Kleber
Author-email: julian.kleber@sail.black
Classifier: Programming Language :: Python :: 3
Classifier: License :: OSI Approved :: GNU General Public License v3 or later (GPLv3+)
Classifier: Operating System :: OS Independent
Requires-Python: >=3.8
License-File: LICENSE.txt
Requires-Dist: Click
Requires-Dist: black
Requires-Dist: autopep8
Requires-Dist: mypy
Requires-Dist: pylint
Requires-Dist: flake8
Requires-Dist: pytest
Requires-Dist: pytest-cov
Requires-Dist: amarium
Requires-Dist: prettify-py
Requires-Dist: twine
Requires-Dist: build
Requires-Dist: emoji
